{
  "openapi": "3.0.1",
  "info": {
    "title": "Homeo_Mart",
    "version": "1.0"
  },
  "paths": {
    "/api/Addresses/get": {
      "post": {
        "tags": [
          "Addresses"
        ],
        "requestBody": {
          "content": {
            "application/json": {
              "schema": {
                "$ref": "#/components/schemas/Address"
              }
            },
            "text/json": {
              "schema": {
                "$ref": "#/components/schemas/Address"
              }
            },
            "application/*+json": {
              "schema": {
                "$ref": "#/components/schemas/Address"
              }
            }
          }
        },
        "responses": {
          "200": {
            "description": "OK"
          }
        }
      }
    },
    "/api/Addresses/insert": {
      "post": {
        "tags": [
          "Addresses"
        ],
        "requestBody": {
          "content": {
            "application/json": {
              "schema": {
                "$ref": "#/components/schemas/Address"
              }
            },
            "text/json": {
              "schema": {
                "$ref": "#/components/schemas/Address"
              }
            },
            "application/*+json": {
              "schema": {
                "$ref": "#/components/schemas/Address"
              }
            }
          }
        },
        "responses": {
          "200": {
            "description": "OK"
          }
        }
      }
    },
    "/api/Addresses/update": {
      "post": {
        "tags": [
          "Addresses"
        ],
        "requestBody": {
          "content": {
            "application/json": {
              "schema": {
                "$ref": "#/components/schemas/Address"
              }
            },
            "text/json": {
              "schema": {
                "$ref": "#/components/schemas/Address"
              }
            },
            "application/*+json": {
              "schema": {
                "$ref": "#/components/schemas/Address"
              }
            }
          }
        },
        "responses": {
          "200": {
            "description": "OK"
          }
        }
      }
    },
    "/api/Addresses/change_status": {
      "post": {
        "tags": [
          "Addresses"
        ],
        "requestBody": {
          "content": {
            "application/json": {
              "schema": {
                "$ref": "#/components/schemas/Address"
              }
            },
            "text/json": {
              "schema": {
                "$ref": "#/components/schemas/Address"
              }
            },
            "application/*+json": {
              "schema": {
                "$ref": "#/components/schemas/Address"
              }
            }
          }
        },
        "responses": {
          "200": {
            "description": "OK"
          }
        }
      }
    },
    "/api/Category/get": {
      "post": {
        "tags": [
          "Category"
        ],
        "responses": {
          "200": {
            "description": "OK"
          }
        }
      }
    },
    "/api/Category/insert": {
      "post": {
        "tags": [
          "Category"
        ],
        "requestBody": {
          "content": {
            "application/json": {
              "schema": {
                "$ref": "#/components/schemas/Category"
              }
            },
            "text/json": {
              "schema": {
                "$ref": "#/components/schemas/Category"
              }
            },
            "application/*+json": {
              "schema": {
                "$ref": "#/components/schemas/Category"
              }
            }
          }
        },
        "responses": {
          "200": {
            "description": "OK"
          }
        }
      }
    },
    "/api/Category/update": {
      "post": {
        "tags": [
          "Category"
        ],
        "requestBody": {
          "content": {
            "application/json": {
              "schema": {
                "$ref": "#/components/schemas/Category"
              }
            },
            "text/json": {
              "schema": {
                "$ref": "#/components/schemas/Category"
              }
            },
            "application/*+json": {
              "schema": {
                "$ref": "#/components/schemas/Category"
              }
            }
          }
        },
        "responses": {
          "200": {
            "description": "OK"
          }
        }
      }
    },
    "/api/Category/change_status": {
      "post": {
        "tags": [
          "Category"
        ],
        "requestBody": {
          "content": {
            "application/json": {
              "schema": {
                "$ref": "#/components/schemas/Category"
              }
            },
            "text/json": {
              "schema": {
                "$ref": "#/components/schemas/Category"
              }
            },
            "application/*+json": {
              "schema": {
                "$ref": "#/components/schemas/Category"
              }
            }
          }
        },
        "responses": {
          "200": {
            "description": "OK"
          }
        }
      }
    },
    "/api/Product/get": {
      "post": {
        "tags": [
          "Product"
        ],
        "requestBody": {
          "content": {
            "application/json": {
              "schema": {
                "$ref": "#/components/schemas/product"
              }
            },
            "text/json": {
              "schema": {
                "$ref": "#/components/schemas/product"
              }
            },
            "application/*+json": {
              "schema": {
                "$ref": "#/components/schemas/product"
              }
            }
          }
        },
        "responses": {
          "200": {
            "description": "OK"
          }
        }
      }
    },
    "/api/Product/insert": {
      "post": {
        "tags": [
          "Product"
        ],
        "requestBody": {
          "content": {
            "application/json": {
              "schema": {
                "$ref": "#/components/schemas/product"
              }
            },
            "text/json": {
              "schema": {
                "$ref": "#/components/schemas/product"
              }
            },
            "application/*+json": {
              "schema": {
                "$ref": "#/components/schemas/product"
              }
            }
          }
        },
        "responses": {
          "200": {
            "description": "OK"
          }
        }
      }
    },
    "/api/Product/update": {
      "post": {
        "tags": [
          "Product"
        ],
        "requestBody": {
          "content": {
            "application/json": {
              "schema": {
                "$ref": "#/components/schemas/product"
              }
            },
            "text/json": {
              "schema": {
                "$ref": "#/components/schemas/product"
              }
            },
            "application/*+json": {
              "schema": {
                "$ref": "#/components/schemas/product"
              }
            }
          }
        },
        "responses": {
          "200": {
            "description": "OK"
          }
        }
      }
    },
    "/api/Product/change_status": {
      "post": {
        "tags": [
          "Product"
        ],
        "requestBody": {
          "content": {
            "application/json": {
              "schema": {
                "$ref": "#/components/schemas/product"
              }
            },
            "text/json": {
              "schema": {
                "$ref": "#/components/schemas/product"
              }
            },
            "application/*+json": {
              "schema": {
                "$ref": "#/components/schemas/product"
              }
            }
          }
        },
        "responses": {
          "200": {
            "description": "OK"
          }
        }
      }
    },
    "/api/User/sign_up": {
      "post": {
        "tags": [
          "User"
        ],
        "requestBody": {
          "content": {
            "application/json": {
              "schema": {
                "$ref": "#/components/schemas/UserSignup"
              }
            },
            "text/json": {
              "schema": {
                "$ref": "#/components/schemas/UserSignup"
              }
            },
            "application/*+json": {
              "schema": {
                "$ref": "#/components/schemas/UserSignup"
              }
            }
          }
        },
        "responses": {
          "200": {
            "description": "OK"
          }
        }
      }
    },
    "/api/User/get_user_by_id": {
      "post": {
        "tags": [
          "User"
        ],
        "requestBody": {
          "content": {
            "application/json": {
              "schema": {
                "type": "integer",
                "format": "int32"
              }
            },
            "text/json": {
              "schema": {
                "type": "integer",
                "format": "int32"
              }
            },
            "application/*+json": {
              "schema": {
                "type": "integer",
                "format": "int32"
              }
            }
          }
        },
        "responses": {
          "200": {
            "description": "OK"
          }
        }
      }
    },
    "/api/User/get_all_users": {
      "post": {
        "tags": [
          "User"
        ],
        "responses": {
          "200": {
            "description": "OK"
          }
        }
      }
    },
    "/api/User/update_user": {
      "put": {
        "tags": [
          "User"
        ],
        "requestBody": {
          "content": {
            "application/json": {
              "schema": {
                "$ref": "#/components/schemas/User"
              }
            },
            "text/json": {
              "schema": {
                "$ref": "#/components/schemas/User"
              }
            },
            "application/*+json": {
              "schema": {
                "$ref": "#/components/schemas/User"
              }
            }
          }
        },
        "responses": {
          "200": {
            "description": "OK"
          }
        }
      }
    },
    "/WeatherForecast": {
      "get": {
        "tags": [
          "WeatherForecast"
        ],
        "operationId": "GetWeatherForecast",
        "responses": {
          "200": {
            "description": "OK",
            "content": {
              "text/plain": {
                "schema": {
                  "type": "array",
                  "items": {
                    "$ref": "#/components/schemas/WeatherForecast"
                  }
                }
              },
              "application/json": {
                "schema": {
                  "type": "array",
                  "items": {
                    "$ref": "#/components/schemas/WeatherForecast"
                  }
                }
              },
              "text/json": {
                "schema": {
                  "type": "array",
                  "items": {
                    "$ref": "#/components/schemas/WeatherForecast"
                  }
                }
              }
            }
          }
        }
      }
    }
  },
  "components": {
    "schemas": {
      "Address": {
        "type": "object",
        "properties": {
          "action_type": {
            "type": "string",
            "nullable": true
          },
          "id": {
            "type": "integer",
            "format": "int32",
            "nullable": true
          },
          "user_id": {
            "type": "integer",
            "format": "int32"
          },
          "address": {
            "type": "string",
            "nullable": true
          },
          "phone_number": {
            "type": "string",
            "nullable": true
          },
          "street": {
            "type": "string",
            "nullable": true
          },
          "city": {
            "type": "string",
            "nullable": true
          },
          "state": {
            "type": "string",
            "nullable": true
          },
          "zip_code": {
            "type": "string",
            "nullable": true
          },
          "country": {
            "type": "string",
            "nullable": true
          },
          "set_as_default": {
            "type": "integer",
            "format": "int32",
            "nullable": true
          },
          "status": {
            "type": "integer",
            "format": "int32",
            "nullable": true
          },
          "created_on": {
            "type": "string",
            "format": "date-time",
            "nullable": true
          },
          "created_by": {
            "type": "integer",
            "format": "int32",
            "nullable": true
          },
          "updated_on": {
            "type": "string",
            "format": "date-time",
            "nullable": true
          },
          "updated_by": {
            "type": "integer",
            "format": "int32",
            "nullable": true
          }
        },
        "additionalProperties": false
      },
      "Category": {
        "type": "object",
        "properties": {
          "id": {
            "type": "integer",
            "format": "int32",
            "nullable": true
          },
          "name": {
            "type": "string",
            "nullable": true
          },
          "code": {
            "type": "string",
            "nullable": true
          },
          "description": {
            "type": "string",
            "nullable": true
          },
          "status": {
            "type": "integer",
            "format": "int32"
          },
          "created_on": {
            "type": "string",
            "format": "date-time"
          },
          "created_by": {
            "type": "integer",
            "format": "int32"
          },
          "updated_on": {
            "type": "string",
            "format": "date-time",
            "nullable": true
          },
          "updated_by": {
            "type": "integer",
            "format": "int32",
            "nullable": true
          }
        },
        "additionalProperties": false
      },
      "User": {
        "type": "object",
        "properties": {
          "userId": {
            "type": "integer",
            "format": "int32"
          },
          "firstName": {
            "type": "string",
            "nullable": true
          },
          "lastName": {
            "type": "string",
            "nullable": true
          },
          "email": {
            "type": "string",
            "nullable": true
          },
          "mobile": {
            "type": "string",
            "nullable": true
          },
          "gender": {
            "type": "string",
            "nullable": true
          },
          "dateOfBirth": {
            "type": "string",
            "format": "date-time"
          },
          "addressLine1": {
            "type": "string",
            "nullable": true
          },
          "addressLine2": {
            "type": "string",
            "nullable": true
          },
          "city": {
            "type": "string",
            "nullable": true
          },
          "state": {
            "type": "string",
            "nullable": true
          },
          "country": {
            "type": "string",
            "nullable": true
          },
          "pincode": {
            "type": "string",
            "nullable": true
          },
          "isActive": {
            "type": "boolean"
          },
          "createdDate": {
            "type": "string",
            "format": "date-time"
          },
          "updatedDate": {
            "type": "string",
            "format": "date-time"
          }
        },
        "additionalProperties": false
      },
      "UserSignup": {
        "type": "object",
        "properties": {
          "firstName": {
            "type": "string",
            "nullable": true
          },
          "lastName": {
            "type": "string",
            "nullable": true
          },
          "email": {
            "type": "string",
            "nullable": true
          },
          "mobile": {
            "type": "string",
            "nullable": true
          },
          "passwordHash": {
            "type": "string",
            "nullable": true
          },
          "gender": {
            "type": "string",
            "nullable": true
          },
          "dateOfBirth": {
            "type": "string",
            "format": "date-time"
          },
          "addressLine1": {
            "type": "string",
            "nullable": true
          },
          "addressLine2": {
            "type": "string",
            "nullable": true
          },
          "city": {
            "type": "string",
            "nullable": true
          },
          "state": {
            "type": "string",
            "nullable": true
          },
          "country": {
            "type": "string",
            "nullable": true
          },
          "pincode": {
            "type": "string",
            "nullable": true
          }
        },
        "additionalProperties": false
      },
      "WeatherForecast": {
        "type": "object",
        "properties": {
          "date": {
            "type": "string",
            "format": "date"
          },
          "temperatureC": {
            "type": "integer",
            "format": "int32"
          },
          "temperatureF": {
            "type": "integer",
            "format": "int32",
            "readOnly": true
          },
          "summary": {
            "type": "string",
            "nullable": true
          }
        },
        "additionalProperties": false
      },
      "product": {
        "type": "object",
        "properties": {
          "action_type": {
            "type": "string",
            "nullable": true
          },
          "id": {
            "type": "integer",
            "format": "int32",
            "nullable": true
          },
          "name": {
            "type": "string",
            "nullable": true
          },
          "code": {
            "type": "string",
            "nullable": true
          },
          "type": {
            "type": "string",
            "nullable": true
          },
          "contributor_name": {
            "type": "string",
            "nullable": true
          },
          "category_id": {
            "type": "integer",
            "format": "int32",
            "nullable": true
          },
          "category_name": {
            "type": "string",
            "nullable": true
          },
          "stock_quantity": {
            "type": "integer",
            "format": "int32",
            "nullable": true
          },
          "price": {
            "type": "number",
            "format": "double",
            "nullable": true
          },
          "discount_type": {
            "type": "string",
            "nullable": true
          },
          "discount": {
            "type": "number",
            "format": "double",
            "nullable": true
          },
          "rating": {
            "type": "number",
            "format": "double",
            "nullable": true
          },
          "description": {
            "type": "string",
            "nullable": true
          },
          "shipping_charges": {
            "type": "integer",
            "format": "int32",
            "nullable": true
          },
          "tax": {
            "type": "integer",
            "format": "int32",
            "nullable": true
          },
          "status": {
            "type": "integer",
            "format": "int32",
            "nullable": true
          },
          "created_on": {
            "type": "string",
            "format": "date-time",
            "nullable": true
          },
          "created_by": {
            "type": "integer",
            "format": "int32",
            "nullable": true
          },
          "updated_by": {
            "type": "integer",
            "format": "int32",
            "nullable": true
          },
          "updated_on": {
            "type": "string",
            "format": "date-time",
            "nullable": true
          },
          "filesjson": {
            "type": "string",
            "nullable": true
          },
          "files": {
            "type": "string",
            "nullable": true
          },
          "files_list": {
            "type": "array",
            "items": {
              "$ref": "#/components/schemas/product_file"
            },
            "nullable": true
          }
        },
        "additionalProperties": false
      },
      "product_file": {
        "type": "object",
        "properties": {
          "id": {
            "type": "integer",
            "format": "int32",
            "nullable": true
          },
          "product_id": {
            "type": "integer",
            "format": "int32",
            "nullable": true
          },
          "file_name": {
            "type": "string",
            "nullable": true
          },
          "file_path": {
            "type": "string",
            "nullable": true
          },
          "file_type": {
            "type": "string",
            "nullable": true
          },
          "status": {
            "type": "integer",
            "format": "int32",
            "nullable": true
          },
          "mode": {
            "type": "integer",
            "format": "int32",
            "nullable": true
          },
          "created_on": {
            "type": "string",
            "nullable": true
          },
          "created_by": {
            "type": "integer",
            "format": "int32",
            "nullable": true
          },
          "updated_on": {
            "type": "string",
            "nullable": true
          },
          "updated_by": {
            "type": "integer",
            "format": "int32",
            "nullable": true
          }
        },
        "additionalProperties": false
      }
    }
  }
}